{"dependencies":[{"name":"./bundle.css","dynamic":true},{"name":"./bundle.js","dynamic":true}],"generated":{"html":"<!DOCTYPE html>\n<html>\n  <head>\n    <meta charset=\"utf-8\">\n    <title>seekwins</title>\n    <link defer=\"\" rel=\"stylesheet\" type=\"text/css\" href=\"/dist/4bda1570f39d2e192bc2d4f882b60d46.css\">\n    <script defer=\"\" src=\"/dist/5f0221f505d3e7e3a63ba63870b6a9ca.js\"></script>\n  </head>\n  <body>\n  </body>\n</html>\n"},"hash":"021956995b92af4a6b7467e9dd6d640e","cacheData":{}}